branchconflicts/Branch.py
branchconflicts/Commit.py
branchconflicts/__init__.py
branchconflicts/main.py
branchconflicts-0.1.6.dist-info/licenses/LICENSE
branchconflicts-0.1.6.dist-info/METADATA
branchconflicts-0.1.6.dist-info/WHEEL
branchconflicts-0.1.6.dist-info/top_level.txt
branchconflicts-0.1.6.dist-info/RECORD
